reminix/__init__.py
reminix/_base_client.py
reminix/_client.py
reminix/_compat.py
reminix/_constants.py
reminix/_exceptions.py
reminix/_files.py
reminix/_models.py
reminix/_qs.py
reminix/_resource.py
reminix/_response.py
reminix/_streaming.py
reminix/_types.py
reminix/_version.py
reminix/pagination.py
reminix/py.typed
reminix/_utils/__init__.py
reminix/_utils/_compat.py
reminix/_utils/_datetime_parse.py
reminix/_utils/_json.py
reminix/_utils/_logs.py
reminix/_utils/_proxy.py
reminix/_utils/_reflection.py
reminix/_utils/_resources_proxy.py
reminix/_utils/_streams.py
reminix/_utils/_sync.py
reminix/_utils/_transform.py
reminix/_utils/_typing.py
reminix/_utils/_utils.py
reminix/lib/.keep
reminix/resources/__init__.py
reminix/resources/agents.py
reminix/resources/client_tokens.py
reminix/resources/conversations.py
reminix/resources/execution_logs.py
reminix/resources/memories.py
reminix/resources/projects.py
reminix/resources/tools.py
reminix/resources/knowledge/__init__.py
reminix/resources/knowledge/knowledge.py
reminix/resources/knowledge/collections/__init__.py
reminix/resources/knowledge/collections/collections.py
reminix/resources/knowledge/collections/documents.py
reminix/types/__init__.py
reminix/types/agent.py
reminix/types/agent_chat_params.py
reminix/types/agent_chat_response.py
reminix/types/agent_config.py
reminix/types/agent_invoke_params.py
reminix/types/agent_invoke_response.py
reminix/types/agent_knowledge_base_config.py
reminix/types/agent_list_params.py
reminix/types/agent_memory_config.py
reminix/types/chat_message.py
reminix/types/chat_message_param.py
reminix/types/client_token_create_params.py
reminix/types/client_token_create_response.py
reminix/types/conversation.py
reminix/types/conversation_list_params.py
reminix/types/conversation_retrieve_response.py
reminix/types/execution_log.py
reminix/types/execution_log_list_params.py
reminix/types/knowledge_search_params.py
reminix/types/knowledge_search_response.py
reminix/types/memory.py
reminix-0.15.0.dist-info/METADATA
reminix-0.15.0.dist-info/WHEEL
reminix-0.15.0.dist-info/licenses/LICENSE
reminix-0.15.0.dist-info/RECORD
